src/GPT.py
src/__init__.py
src/__main__.py
src/prompts.py
WingmanGPT-2.0.0.dist-info/LICENSE
WingmanGPT-2.0.0.dist-info/METADATA
WingmanGPT-2.0.0.dist-info/WHEEL
WingmanGPT-2.0.0.dist-info/entry_points.txt
WingmanGPT-2.0.0.dist-info/top_level.txt
WingmanGPT-2.0.0.dist-info/RECORD
