Metadata-Version: 2.1
Name: WingmanGPT
Version: 2.0.0
Summary: A chatbot that uses ChatGPT to help you find a date.
Author-email: Ben Schwartz <btschwartz12@gmail.com>, Ryan Baxter <rybaxter@umich.edu>, Paul Chafetz <pchafetz@umich.edu>
License: MIT License
Project-URL: Homepage, https://github.com/btschwartz12/WingmanGPT
Keywords: chatgpt,text,date
Classifier: License :: OSI Approved :: MIT License
Classifier: Programming Language :: Python
Classifier: Programming Language :: Python :: 3
Requires-Python: >=3.8
License-File: LICENSE
Requires-Dist: requests
